papermill_sftp/__init__.py
papermill_sftp-0.0.1.dist-info/WHEEL
papermill_sftp-0.0.1.dist-info/METADATA
papermill_sftp-0.0.1.dist-info/RECORD
