Metadata-Version: 2.1
Name: papermill-sftp
Version: 0.0.1
Summary: A papermill SFTP I/O handler.
Home-page: UNKNOWN
License: UNKNOWN
Author: Jan Freyberg
Author-email: jan.freyberg@gmail.com
Requires-Python: >=3.5,<4.0
Classifier: Programming Language :: Python :: 3
Classifier: Programming Language :: Python :: 3.5
Classifier: Programming Language :: Python :: 3.6
Classifier: Programming Language :: Python :: 3.7
Requires-Dist: pysftp (>=0.2.9,<0.3.0)
